limecore/core/rollback_exception.py
limecore/core/types.py
limecore_core-0.2.1.dist-info/LICENSE.txt
limecore_core-0.2.1.dist-info/METADATA
limecore_core-0.2.1.dist-info/WHEEL
limecore_core-0.2.1.dist-info/top_level.txt
limecore_core-0.2.1.dist-info/RECORD
